{
  "metadata": {
    "description": null,
    "title": "Bienvenidos a Casa Felisa",
    "languages_detected": [
      "en"
    ]
  },
  "pages": [
    {
      "description": null,
      "title": "Bienvenidos a Casa Felisa",
      "url": "http://www.casafelisa.es/",
      "language": "en",
      "content": "Bienvenidos a Casa Felisa Disfruta en nuestro acogedor jardín de una velada inolvidable Nuestro restaurante, especializado en cocina tradicional, ofrece un menú variado de la más alta cocina gallega. Productos frescos de gran calidad: carnes , pescados, legumbres, hortalizas... acompañados de los mejores vinos Bienvenidos a Casa Felisa No front page content has been created yet. El Hostal Casa Felisa dispone de 12 habitaciones equipadas con todas las comodidades para que tu estancia en nuestra pensión sea lo más grata posible. + info El Restaurante En Casa Felisa respirarás un ambiente familiar. En nuestro restaurante podrás disfrutar platos de la cocina tradicional gallega, haciendo de tu estancia en Casa Felisa una experiencia para no olvidar. + info Nuestros Menus MENÚ PARA GRUPOS MENÚ ESPECIAL COCINA DE INVIERNO SERVICIO DE COMIDAS A DOMICILIO 981 582 602 inicio habitaciones menu carta contactar Calle Porta da Pena, 5 Santiago de Compostela 15704 casafelisa@hotmail.com Back to top",
      "headings": [
        "Disfruta en nuestro acogedor jardín de una velada inolvidable",
        "Bienvenidos a Casa Felisa",
        "Nuestros Menus",
        "SERVICIO DE COMIDAS A DOMICILIO",
        "981 582 602"
      ],
      "content_length": 999
    }
  ],
  "pages_crawled": 1,
  "has_english_version": true,
  "total_content_length": 999,
  "crawled_at": "2026-01-28T14:59:46.477746Z"
}